plexer_cli/__init__.py
plexer_cli/artifact.py
plexer_cli/const.py
plexer_cli/file_manager.py
plexer_cli/main.py
plexer_cli/metadata.py
plexer_cli-0.0.3.post5.dist-info/METADATA
plexer_cli-0.0.3.post5.dist-info/WHEEL
plexer_cli-0.0.3.post5.dist-info/entry_points.txt
plexer_cli-0.0.3.post5.dist-info/licenses/LICENSE
plexer_cli-0.0.3.post5.dist-info/RECORD
