Metadata-Version: 2.3
Name: plexer_cli
Version: 0.0.3.post5
Summary: Normalize media files for use with Plex Media Server
Project-URL: Repository, https://github.com/magneticstain/plexer.git
Project-URL: Documentation, https://github.com/magneticstain/plexer#readme
Project-URL: Issues, https://github.com/magneticstain/plexer/issues
Project-URL: Source, https://github.com/magneticstain/plexer
Author-email: Josh Carlson <837837+magneticstain@users.noreply.github.com>
License-Expression: MIT
License-File: LICENSE
Keywords: catagorization,formatting,media,organization,plex
Classifier: Development Status :: 2 - Pre-Alpha
Classifier: Environment :: Console
Classifier: Framework :: Hatch
Classifier: Framework :: Pytest
Classifier: Framework :: tox
Classifier: Intended Audience :: System Administrators
Classifier: License :: OSI Approved :: MIT License
Classifier: Operating System :: Unix
Classifier: Programming Language :: Python
Classifier: Programming Language :: Python :: 3.9
Classifier: Programming Language :: Python :: 3.10
Classifier: Programming Language :: Python :: 3.11
Classifier: Programming Language :: Python :: 3.12
Classifier: Topic :: Utilities
Requires-Python: >=3.9
Requires-Dist: logzero~=1.7.0
Requires-Dist: python-magic~=0.4.27
